Workbook

Sheet Dashboard
A1: AP / AR TRACKER — DASHBOARD
A2: =Settings!$B$4 | J2: Report Date: | K2: =Settings!$B$5
A4: Total AR Outstanding (RM) | E4: Total AP Outstanding (RM) | I4: Net Position: AR minus AP (RM)
A5: =SUMIF('AR Ledger'!$N$3:$N$1000,"<>Paid",'AR Ledger'!$K$3:$K$1000) | E5: =SUMIF('AP Ledger'!$N$3:$N$1000,"<>Paid",'AP Ledger'!$K$3:$K$1000) | I5: =SUMIF('AR Ledger'!$N$3:$N$1000,"<>Paid",'AR Ledger'!$K$3:$K$1000)-SUMIF('AP Ledger'!$N$3:$N$1000,"<>Paid",'AP Ledger'!$K$3:$K$1000)
A6: Total AR Overdue 90+ Days (RM) | E6: Number of Overdue AR Invoices | I6: Collection Rate (Paid / Total Invoiced)
A7: =SUMIF('AR Ledger'!$M$3:$M$1000,"90+ Days",'AR Ledger'!$K$3:$K$1000) | E7: =COUNTIF('AR Ledger'!$N$3:$N$1000,"Overdue")+COUNTIF('AR Ledger'!$N$3:$N$1000,"Partial") | I7: =IFERROR(1-SUMIF('AR Ledger'!$N$3:$N$1000,"<>Paid",'AR Ledger'!$K$3:$K$1000)/SUM('AR Ledger'!$H$3:$H$1000),0)
A45: Aging Bucket | B45: Outstanding (RM)
A46: Current | B46: =SUMIF('AR Ledger'!$M$3:$M$1000,"Current",'AR Ledger'!$K$3:$K$1000)
A47: 1-30 Days | B47: =SUMIF('AR Ledger'!$M$3:$M$1000,"1-30 Days",'AR Ledger'!$K$3:$K$1000)
A48: 31-60 Days | B48: =SUMIF('AR Ledger'!$M$3:$M$1000,"31-60 Days",'AR Ledger'!$K$3:$K$1000)
A49: 61-90 Days | B49: =SUMIF('AR Ledger'!$M$3:$M$1000,"61-90 Days",'AR Ledger'!$K$3:$K$1000)
A50: 90+ Days | B50: =SUMIF('AR Ledger'!$M$3:$M$1000,"90+ Days",'AR Ledger'!$K$3:$K$1000)
A52: Aging Bucket | B52: Outstanding (RM)
A53: Current | B53: =SUMIF('AP Ledger'!$M$3:$M$1000,"Current",'AP Ledger'!$K$3:$K$1000)
A54: 1-30 Days | B54: =SUMIF('AP Ledger'!$M$3:$M$1000,"1-30 Days",'AP Ledger'!$K$3:$K$1000)
A55: 31-60 Days | B55: =SUMIF('AP Ledger'!$M$3:$M$1000,"31-60 Days",'AP Ledger'!$K$3:$K$1000)
A56: 61-90 Days | B56: =SUMIF('AP Ledger'!$M$3:$M$1000,"61-90 Days",'AP Ledger'!$K$3:$K$1000)
A57: 90+ Days | B57: =SUMIF('AP Ledger'!$M$3:$M$1000,"90+ Days",'AP Ledger'!$K$3:$K$1000)

Sheet AR Ledger
A1: AR Ledger — Invoice & Payment Records
A2: Invoice Number | B2: Invoice Date | C2: Due Date | D2: Client Name | E2: Description | F2: Amount (excl. Tax) | G2: Tax Amount | H2: Total Amount | I2: Payment Date | J2: Payment Amount | K2: Outstanding Balance | L2: Days Overdue | M2: Aging Bucket | N2: Status | O2: Notes
A3: INV-001 | B3: 46027 | C3: 46037 | D3: Axiata Group Berhad | E3: Software Development | F3: 5000 | G3: =F3*Settings!$B$6/100 | H3: =F3+G3 | I3: 46042 | J3: 5300 | K3: =H3-J3 | L3: =IF(K3<=0,0,MAX(0,TODAY()-C3)) | M3: =IF(K3<=0,"Paid",IF(L3=0,"Current",IF(L3<=Settings!$B$8,"1-30 Days",IF(L3<=Settings!$B$9,"31-60 Days",IF(L3<=Settings!$B$10,"61-90 Days","90+ Days"))))) | N3: =IF(K3<=0,"Paid",IF(J3>0,"Partial",IF(L3>0,"Overdue","Outstanding")))
A4: INV-002 | B4: 46042 | C4: 46057 | D4: Tenaga Nasional Berhad | E4: Consulting Services | F4: 8000 | G4: =F4*Settings!$B$6/100 | H4: =F4+G4 | I4: 46073 | J4: 4000 | K4: =H4-J4 | L4: =IF(K4<=0,0,MAX(0,TODAY()-C4)) | M4: =IF(K4<=0,"Paid",IF(L4=0,"Current",IF(L4<=Settings!$B$8,"1-30 Days",IF(L4<=Settings!$B$9,"31-60 Days",IF(L4<=Settings!$B$10,"61-90 Days","90+ Days"))))) | N4: =IF(K4<=0,"Paid",IF(J4>0,"Partial",IF(L4>0,"Overdue","Outstanding"))) | O4: Follow up required
A5: INV-003 | B5: 46063 | C5: 46078 | D5: CIMB Group Holdings | E5: Staff Training | F5: 3500 | G5: =F5*Settings!$B$6/100 | H5: =F5+G5 | J5: 0 | K5: =H5-J5 | L5: =IF(K5<=0,0,MAX(0,TODAY()-C5)) | M5: =IF(K5<=0,"Paid",IF(L5=0,"Current",IF(L5<=Settings!$B$8,"1-30 Days",IF(L5<=Settings!$B$9,"31-60 Days",IF(L5<=Settings!$B$10,"61-90 Days","90+ Days"))))) | N5: =IF(K5<=0,"Paid",IF(J5>0,"Partial",IF(L5>0,"Overdue","Outstanding")))
A6: INV-004 | B6: 46082 | C6: 46096 | D6: Axiata Group Berhad | E6: System Maintenance | F6: 2000 | G6: =F6*Settings!$B$6/100 | H6: =F6+G6 | J6: 0 | K6: =H6-J6 | L6: =IF(K6<=0,0,MAX(0,TODAY()-C6)) | M6: =IF(K6<=0,"Paid",IF(L6=0,"Current",IF(L6<=Settings!$B$8,"1-30 Days",IF(L6<=Settings!$B$9,"31-60 Days",IF(L6<=Settings!$B$10,"61-90 Days","90+ Days"))))) | N6: =IF(K6<=0,"Paid",IF(J6>0,"Partial",IF(L6>0,"Overdue","Outstanding")))
A7: INV-005 | B7: 46101 | C7: 46131 | D7: Petronas Dagangan | E7: Software License | F7: 12000 | G7: =F7*Settings!$B$6/100 | H7: =F7+G7 | J7: 0 | K7: =H7-J7 | L7: =IF(K7<=0,0,MAX(0,TODAY()-C7)) | M7: =IF(K7<=0,"Paid",IF(L7=0,"Current",IF(L7<=Settings!$B$8,"1-30 Days",IF(L7<=Settings!$B$9,"31-60 Days",IF(L7<=Settings!$B$10,"61-90 Days","90+ Days"))))) | N7: =IF(K7<=0,"Paid",IF(J7>0,"Partial",IF(L7>0,"Overdue","Outstanding")))

Sheet AP Ledger
A1: AP Ledger — Invoice & Payment Records
A2: Bill Number | B2: Bill Date | C2: Due Date | D2: Vendor Name | E2: Description | F2: Amount (excl. Tax) | G2: Tax Amount | H2: Total Amount | I2: Payment Date | J2: Payment Amount | K2: Outstanding Balance | L2: Days Overdue | M2: Aging Bucket | N2: Status | O2: Notes
A3: BILL-001 | B3: 46030 | C3: 46040 | D3: Pos Malaysia Berhad | E3: Courier Services | F3: 500 | G3: =F3*Settings!$B$6/100 | H3: =F3+G3 | I3: 46042 | J3: 530 | K3: =H3-J3 | L3: =IF(K3<=0,0,MAX(0,TODAY()-C3)) | M3: =IF(K3<=0,"Paid",IF(L3=0,"Current",IF(L3<=Settings!$B$8,"1-30 Days",IF(L3<=Settings!$B$9,"31-60 Days",IF(L3<=Settings!$B$10,"61-90 Days","90+ Days"))))) | N3: =IF(K3<=0,"Paid",IF(J3>0,"Partial",IF(L3>0,"Overdue","Outstanding")))
A4: BILL-002 | B4: 46047 | C4: 46062 | D4: Telekom Malaysia | E4: Internet Subscription | F4: 350 | G4: =F4*Settings!$B$6/100 | H4: =F4+G4 | I4: 46065 | J4: 371 | K4: =H4-J4 | L4: =IF(K4<=0,0,MAX(0,TODAY()-C4)) | M4: =IF(K4<=0,"Paid",IF(L4=0,"Current",IF(L4<=Settings!$B$8,"1-30 Days",IF(L4<=Settings!$B$9,"31-60 Days",IF(L4<=Settings!$B$10,"61-90 Days","90+ Days"))))) | N4: =IF(K4<=0,"Paid",IF(J4>0,"Partial",IF(L4>0,"Overdue","Outstanding")))
A5: BILL-003 | B5: 46061 | C5: 46075 | D5: Digi Telecommunications | E5: Mobile Services | F5: 200 | G5: =F5*Settings!$B$6/100 | H5: =F5+G5 | J5: 0 | K5: =H5-J5 | L5: =IF(K5<=0,0,MAX(0,TODAY()-C5)) | M5: =IF(K5<=0,"Paid",IF(L5=0,"Current",IF(L5<=Settings!$B$8,"1-30 Days",IF(L5<=Settings!$B$9,"31-60 Days",IF(L5<=Settings!$B$10,"61-90 Days","90+ Days"))))) | N5: =IF(K5<=0,"Paid",IF(J5>0,"Partial",IF(L5>0,"Overdue","Outstanding")))
A6: BILL-004 | B6: 46086 | C6: 46100 | D6: Syabas Water Supply | E6: Monthly Water Bill | F6: 150 | G6: =F6*Settings!$B$6/100 | H6: =F6+G6 | J6: 0 | K6: =H6-J6 | L6: =IF(K6<=0,0,MAX(0,TODAY()-C6)) | M6: =IF(K6<=0,"Paid",IF(L6=0,"Current",IF(L6<=Settings!$B$8,"1-30 Days",IF(L6<=Settings!$B$9,"31-60 Days",IF(L6<=Settings!$B$10,"61-90 Days","90+ Days"))))) | N6: =IF(K6<=0,"Paid",IF(J6>0,"Partial",IF(L6>0,"Overdue","Outstanding")))
A7: BILL-005 | B7: 46096 | C7: 46126 | D7: TNB (Electricity) | E7: Electricity Bill | F7: 800 | G7: =F7*Settings!$B$6/100 | H7: =F7+G7 | J7: 0 | K7: =H7-J7 | L7: =IF(K7<=0,0,MAX(0,TODAY()-C7)) | M7: =IF(K7<=0,"Paid",IF(L7=0,"Current",IF(L7<=Settings!$B$8,"1-30 Days",IF(L7<=Settings!$B$9,"31-60 Days",IF(L7<=Settings!$B$10,"61-90 Days","90+ Days"))))) | N7: =IF(K7<=0,"Paid",IF(J7>0,"Partial",IF(L7>0,"Overdue","Outstanding")))

Sheet AR Aging Report
A1: AR Aging Report — Outstanding Balance Summary
A2: Report Date: | B2: =Settings!$B$5
A4: Entity Name | B4: Total Outstanding | C4: Current | D4: 1-30 Days | E4: 31-60 Days | F4: 61-90 Days | G4: 90+ Days
A5: Axiata Group Berhad | B5: =SUMIF('AR Ledger'!$D:$D,A5,'AR Ledger'!$K:$K) | C5: =SUMIFS('AR Ledger'!$K:$K,'AR Ledger'!$D:$D,A5,'AR Ledger'!$M:$M,"Current") | D5: =SUMIFS('AR Ledger'!$K:$K,'AR Ledger'!$D:$D,A5,'AR Ledger'!$M:$M,"1-30 Days") | E5: =SUMIFS('AR Ledger'!$K:$K,'AR Ledger'!$D:$D,A5,'AR Ledger'!$M:$M,"31-60 Days") | F5: =SUMIFS('AR Ledger'!$K:$K,'AR Ledger'!$D:$D,A5,'AR Ledger'!$M:$M,"61-90 Days") | G5: =SUMIFS('AR Ledger'!$K:$K,'AR Ledger'!$D:$D,A5,'AR Ledger'!$M:$M,"90+ Days")
A6: Tenaga Nasional Berhad | B6: =SUMIF('AR Ledger'!$D:$D,A6,'AR Ledger'!$K:$K) | C6: =SUMIFS('AR Ledger'!$K:$K,'AR Ledger'!$D:$D,A6,'AR Ledger'!$M:$M,"Current") | D6: =SUMIFS('AR Ledger'!$K:$K,'AR Ledger'!$D:$D,A6,'AR Ledger'!$M:$M,"1-30 Days") | E6: =SUMIFS('AR Ledger'!$K:$K,'AR Ledger'!$D:$D,A6,'AR Ledger'!$M:$M,"31-60 Days") | F6: =SUMIFS('AR Ledger'!$K:$K,'AR Ledger'!$D:$D,A6,'AR Ledger'!$M:$M,"61-90 Days") | G6: =SUMIFS('AR Ledger'!$K:$K,'AR Ledger'!$D:$D,A6,'AR Ledger'!$M:$M,"90+ Days")
A7: CIMB Group Holdings | B7: =SUMIF('AR Ledger'!$D:$D,A7,'AR Ledger'!$K:$K) | C7: =SUMIFS('AR Ledger'!$K:$K,'AR Ledger'!$D:$D,A7,'AR Ledger'!$M:$M,"Current") | D7: =SUMIFS('AR Ledger'!$K:$K,'AR Ledger'!$D:$D,A7,'AR Ledger'!$M:$M,"1-30 Days") | E7: =SUMIFS('AR Ledger'!$K:$K,'AR Ledger'!$D:$D,A7,'AR Ledger'!$M:$M,"31-60 Days") | F7: =SUMIFS('AR Ledger'!$K:$K,'AR Ledger'!$D:$D,A7,'AR Ledger'!$M:$M,"61-90 Days") | G7: =SUMIFS('AR Ledger'!$K:$K,'AR Ledger'!$D:$D,A7,'AR Ledger'!$M:$M,"90+ Days")
A8: Petronas Dagangan | B8: =SUMIF('AR Ledger'!$D:$D,A8,'AR Ledger'!$K:$K) | C8: =SUMIFS('AR Ledger'!$K:$K,'AR Ledger'!$D:$D,A8,'AR Ledger'!$M:$M,"Current") | D8: =SUMIFS('AR Ledger'!$K:$K,'AR Ledger'!$D:$D,A8,'AR Ledger'!$M:$M,"1-30 Days") | E8: =SUMIFS('AR Ledger'!$K:$K,'AR Ledger'!$D:$D,A8,'AR Ledger'!$M:$M,"31-60 Days") | F8: =SUMIFS('AR Ledger'!$K:$K,'AR Ledger'!$D:$D,A8,'AR Ledger'!$M:$M,"61-90 Days") | G8: =SUMIFS('AR Ledger'!$K:$K,'AR Ledger'!$D:$D,A8,'AR Ledger'!$M:$M,"90+ Days")
A9: Top Glove Corporation | B9: =SUMIF('AR Ledger'!$D:$D,A9,'AR Ledger'!$K:$K) | C9: =SUMIFS('AR Ledger'!$K:$K,'AR Ledger'!$D:$D,A9,'AR Ledger'!$M:$M,"Current") | D9: =SUMIFS('AR Ledger'!$K:$K,'AR Ledger'!$D:$D,A9,'AR Ledger'!$M:$M,"1-30 Days") | E9: =SUMIFS('AR Ledger'!$K:$K,'AR Ledger'!$D:$D,A9,'AR Ledger'!$M:$M,"31-60 Days") | F9: =SUMIFS('AR Ledger'!$K:$K,'AR Ledger'!$D:$D,A9,'AR Ledger'!$M:$M,"61-90 Days") | G9: =SUMIFS('AR Ledger'!$K:$K,'AR Ledger'!$D:$D,A9,'AR Ledger'!$M:$M,"90+ Days")
A10: TOTAL | B10: =SUM(B5:B9) | C10: =SUM(C5:C9) | D10: =SUM(D5:D9) | E10: =SUM(E5:E9) | F10: =SUM(F5:F9) | G10: =SUM(G5:G9)

Sheet AP Aging Report
A1: AP Aging Report — Outstanding Balance Summary
A2: Report Date: | B2: =Settings!$B$5
A4: Entity Name | B4: Total Outstanding | C4: Current | D4: 1-30 Days | E4: 31-60 Days | F4: 61-90 Days | G4: 90+ Days | H4: Next Payment Due
A5: Pos Malaysia Berhad | B5: =SUMIF('AP Ledger'!$D:$D,A5,'AP Ledger'!$K:$K) | C5: =SUMIFS('AP Ledger'!$K:$K,'AP Ledger'!$D:$D,A5,'AP Ledger'!$M:$M,"Current") | D5: =SUMIFS('AP Ledger'!$K:$K,'AP Ledger'!$D:$D,A5,'AP Ledger'!$M:$M,"1-30 Days") | E5: =SUMIFS('AP Ledger'!$K:$K,'AP Ledger'!$D:$D,A5,'AP Ledger'!$M:$M,"31-60 Days") | F5: =SUMIFS('AP Ledger'!$K:$K,'AP Ledger'!$D:$D,A5,'AP Ledger'!$M:$M,"61-90 Days") | G5: =SUMIFS('AP Ledger'!$K:$K,'AP Ledger'!$D:$D,A5,'AP Ledger'!$M:$M,"90+ Days") | H5: =IFERROR(MINIFS('AP Ledger'!$C:$C,'AP Ledger'!$D:$D,A5,'AP Ledger'!$N:$N,"<>Paid"),"")
A6: Telekom Malaysia | B6: =SUMIF('AP Ledger'!$D:$D,A6,'AP Ledger'!$K:$K) | C6: =SUMIFS('AP Ledger'!$K:$K,'AP Ledger'!$D:$D,A6,'AP Ledger'!$M:$M,"Current") | D6: =SUMIFS('AP Ledger'!$K:$K,'AP Ledger'!$D:$D,A6,'AP Ledger'!$M:$M,"1-30 Days") | E6: =SUMIFS('AP Ledger'!$K:$K,'AP Ledger'!$D:$D,A6,'AP Ledger'!$M:$M,"31-60 Days") | F6: =SUMIFS('AP Ledger'!$K:$K,'AP Ledger'!$D:$D,A6,'AP Ledger'!$M:$M,"61-90 Days") | G6: =SUMIFS('AP Ledger'!$K:$K,'AP Ledger'!$D:$D,A6,'AP Ledger'!$M:$M,"90+ Days") | H6: =IFERROR(MINIFS('AP Ledger'!$C:$C,'AP Ledger'!$D:$D,A6,'AP Ledger'!$N:$N,"<>Paid"),"")
A7: Digi Telecommunications | B7: =SUMIF('AP Ledger'!$D:$D,A7,'AP Ledger'!$K:$K) | C7: =SUMIFS('AP Ledger'!$K:$K,'AP Ledger'!$D:$D,A7,'AP Ledger'!$M:$M,"Current") | D7: =SUMIFS('AP Ledger'!$K:$K,'AP Ledger'!$D:$D,A7,'AP Ledger'!$M:$M,"1-30 Days") | E7: =SUMIFS('AP Ledger'!$K:$K,'AP Ledger'!$D:$D,A7,'AP Ledger'!$M:$M,"31-60 Days") | F7: =SUMIFS('AP Ledger'!$K:$K,'AP Ledger'!$D:$D,A7,'AP Ledger'!$M:$M,"61-90 Days") | G7: =SUMIFS('AP Ledger'!$K:$K,'AP Ledger'!$D:$D,A7,'AP Ledger'!$M:$M,"90+ Days") | H7: =IFERROR(MINIFS('AP Ledger'!$C:$C,'AP Ledger'!$D:$D,A7,'AP Ledger'!$N:$N,"<>Paid"),"")
A8: Syabas Water Supply | B8: =SUMIF('AP Ledger'!$D:$D,A8,'AP Ledger'!$K:$K) | C8: =SUMIFS('AP Ledger'!$K:$K,'AP Ledger'!$D:$D,A8,'AP Ledger'!$M:$M,"Current") | D8: =SUMIFS('AP Ledger'!$K:$K,'AP Ledger'!$D:$D,A8,'AP Ledger'!$M:$M,"1-30 Days") | E8: =SUMIFS('AP Ledger'!$K:$K,'AP Ledger'!$D:$D,A8,'AP Ledger'!$M:$M,"31-60 Days") | F8: =SUMIFS('AP Ledger'!$K:$K,'AP Ledger'!$D:$D,A8,'AP Ledger'!$M:$M,"61-90 Days") | G8: =SUMIFS('AP Ledger'!$K:$K,'AP Ledger'!$D:$D,A8,'AP Ledger'!$M:$M,"90+ Days") | H8: =IFERROR(MINIFS('AP Ledger'!$C:$C,'AP Ledger'!$D:$D,A8,'AP Ledger'!$N:$N,"<>Paid"),"")
A9: TNB (Electricity) | B9: =SUMIF('AP Ledger'!$D:$D,A9,'AP Ledger'!$K:$K) | C9: =SUMIFS('AP Ledger'!$K:$K,'AP Ledger'!$D:$D,A9,'AP Ledger'!$M:$M,"Current") | D9: =SUMIFS('AP Ledger'!$K:$K,'AP Ledger'!$D:$D,A9,'AP Ledger'!$M:$M,"1-30 Days") | E9: =SUMIFS('AP Ledger'!$K:$K,'AP Ledger'!$D:$D,A9,'AP Ledger'!$M:$M,"31-60 Days") | F9: =SUMIFS('AP Ledger'!$K:$K,'AP Ledger'!$D:$D,A9,'AP Ledger'!$M:$M,"61-90 Days") | G9: =SUMIFS('AP Ledger'!$K:$K,'AP Ledger'!$D:$D,A9,'AP Ledger'!$M:$M,"90+ Days") | H9: =IFERROR(MINIFS('AP Ledger'!$C:$C,'AP Ledger'!$D:$D,A9,'AP Ledger'!$N:$N,"<>Paid"),"")
A10: TOTAL | B10: =SUM(B5:B9) | C10: =SUM(C5:C9) | D10: =SUM(D5:D9) | E10: =SUM(E5:E9) | F10: =SUM(F5:F9) | G10: =SUM(G5:G9) | H10: =SUM(H5:H9)

Sheet Settings
A1: AP/AR Tracker — Settings
A3: Setting | B3: Value | C3: Notes
A4: Company Name | B4: Your Company Sdn Bhd | C4: Shown in all report headers
A5: Report Date | B5: =TODAY() | C5: Auto-set to today; override if needed
A6: Tax Rate (%) | B6: 6 | C6: SST rate applied to invoice amounts
A7: Currency | B7: RM | C7: Display currency symbol
A8: Aging Threshold 1 | B8: 30 | C8: Upper limit for first overdue bucket
A9: Aging Threshold 2 | B9: 60 | C9: Upper limit for second overdue bucket
A10: Aging Threshold 3 | B10: 90 | C10: Upper limit for third overdue bucket
A11: AR Invoice Prefix | B11: INV- | C11: Auto-number prefix for AR invoices
A12: AP Bill Prefix | B12: BILL- | C12: Auto-number prefix for AP bills

Sheet Lookup Tables
A1: Lookup Tables — Reference Data
A3: Client List | D3: Vendor List | G3: Payment Terms | J3: Account Codes
A4: Client ID | B4: Client Name | D4: Vendor ID | E4: Vendor Name | G4: Term Code | H4: Description | J4: Code | K4: Account Name
A5: CL-001 | B5: Axiata Group Berhad | D5: VD-001 | E5: Pos Malaysia Berhad | G5: NET7 | H5: Payment due in 7 days | J5: 1100 | K5: Accounts Receivable
A6: CL-002 | B6: Tenaga Nasional Berhad | D6: VD-002 | E6: Telekom Malaysia | G6: NET14 | H6: Payment due in 14 days | J6: 2100 | K6: Accounts Payable
A7: CL-003 | B7: CIMB Group Holdings | D7: VD-003 | E7: Digi Telecommunications | G7: NET30 | H7: Payment due in 30 days | J7: 4000 | K7: Sales Revenue
A8: CL-004 | B8: Petronas Dagangan | D8: VD-004 | E8: Syabas Water Supply | G8: NET60 | H8: Payment due in 60 days | J8: 5000 | K8: Cost of Goods Sold
A9: CL-005 | B9: Top Glove Corporation | D9: VD-005 | E9: TNB (Electricity) | G9: COD | H9: Cash on delivery | J9: 6000 | K9: Operating Expenses
G10: EOM | H10: End of month | J10: 2200 | K10: SST Payable
